README.rst
setup.py
mahisarithmetic/__init__.py
mahisarithmetic.egg-info/PKG-INFO
mahisarithmetic.egg-info/SOURCES.txt
mahisarithmetic.egg-info/dependency_links.txt
mahisarithmetic.egg-info/not-zip-safe
mahisarithmetic.egg-info/top_level.txt