Metadata-Version: 1.0
Name: mahisarithmetic
Version: 1.0
Summary: Basic Arithmetic Operations Library
Home-page: https://github.com/mahi4github/mahisarithmetic
Author: Mahi
Author-email: mthammali@gmail.com
License: MIT
Platform: UNKNOWN
